odoo10_addon_sale_comment_template-10.0.1.2.0-py2.7-nspkg.pth
odoo/addons/sale_comment_template/README.rst
odoo/addons/sale_comment_template/__init__.py
odoo/addons/sale_comment_template/__manifest__.py
odoo/addons/sale_comment_template/i18n/es.po
odoo/addons/sale_comment_template/i18n/fr.po
odoo/addons/sale_comment_template/i18n/sale_comment_template.pot
odoo/addons/sale_comment_template/models/__init__.py
odoo/addons/sale_comment_template/models/sale_order.py
odoo/addons/sale_comment_template/security/ir.model.access.csv
odoo/addons/sale_comment_template/static/description/icon.png
odoo/addons/sale_comment_template/static/src/css/sale.css
odoo/addons/sale_comment_template/tests/__init__.py
odoo/addons/sale_comment_template/tests/test_sale_order_report.py
odoo/addons/sale_comment_template/views/base_comment_template_view.xml
odoo/addons/sale_comment_template/views/report_saleorder.xml
odoo/addons/sale_comment_template/views/sale_order_view.xml
odoo10_addon_sale_comment_template-10.0.1.2.0.dist-info/METADATA
odoo10_addon_sale_comment_template-10.0.1.2.0.dist-info/RECORD
odoo10_addon_sale_comment_template-10.0.1.2.0.dist-info/WHEEL
odoo10_addon_sale_comment_template-10.0.1.2.0.dist-info/namespace_packages.txt
odoo10_addon_sale_comment_template-10.0.1.2.0.dist-info/top_level.txt
