Metadata-Version: 2.1
Name: odoo10-addon-sale-comment-template
Version: 10.0.1.2.0
Summary: Comments texts templates on Sale documents
Home-page: https://github.com/OCA/sale-reporting
Author: Camptocamp, Odoo Community Association (OCA)
Author-email: support@odoo-community.org
License: AGPL-3
Platform: UNKNOWN
Classifier: Programming Language :: Python
Classifier: Framework :: Odoo
Classifier: License :: OSI Approved :: GNU Affero General Public License v3
Requires-Python: ~=2.7
Requires-Dist: odoo10-addon-invoice-comment-template
Requires-Dist: odoo (<10.1dev,>=10.0)
